{
    "uuids": {
        "phone_id": "9df167bb-7482-4f21-9e2c-1672fe674c87",
        "uuid": "aced2cdc-32f0-4e29-bb59-871e6a95ce5e",
        "client_session_id": "d5332578-f81d-450a-b0ad-0b0476f1ff2b",
        "advertising_id": "02792131-0572-4538-b433-23a0e78c1636",
        "android_device_id": "android-e3994ec7957430c4",
        "request_id": "3234699a-ff5a-4b54-bb51-80d2a1d41826",
        "tray_session_id": "ecd71e7c-d494-4f96-b48a-2360c5b269e0"
    },
    "mid": "aJYNQQABAAGFCeL1ZQ8YBNkwsnjC",
    "ig_u_rur": null,
    "ig_www_claim": null,
    "authorization_data": {
        "ds_user_id": "76254634374",
        "sessionid": "76254634374%3Ah8FTT9vZrn8Jv1%3A6%3AAYcCguFgqV-nPdSc-ZeZByd3f1Xq-6RjVB1aUxtdNw"
    },
    "cookies": {},
    "last_login": 1754664271.5559604,
    "device_settings": {
        "app_version": "269.0.0.18.75",
        "android_version": 26,
        "android_release": "8.0.0",
        "dpi": "480dpi",
        "resolution": "1080x1920",
        "manufacturer": "OnePlus",
        "device": "devitron",
        "model": "6T Dev",
        "cpu": "qcom",
        "version_code": "314665256"
    },
    "user_agent": "Instagram 269.0.0.18.75 Android (26/8.0.0; 480dpi; 1080x1920; OnePlus; 6T Dev; devitron; qcom; en_US; 314665256)",
    "country": "US",
    "country_code": 1,
    "locale": "en_US",
    "timezone_offset": -14400
}